pycamunda/__init__.py
pycamunda/activityinst.py
pycamunda/auth.py
pycamunda/base.py
pycamunda/batch.py
pycamunda/casedef.py
pycamunda/caseinst.py
pycamunda/condition.py
pycamunda/decisiondef.py
pycamunda/decisionreqdef.py
pycamunda/deployment.py
pycamunda/execution.py
pycamunda/externaltask.py
pycamunda/filter.py
pycamunda/group.py
pycamunda/identity.py
pycamunda/incident.py
pycamunda/instruction.py
pycamunda/message.py
pycamunda/migration.py
pycamunda/processdef.py
pycamunda/processinst.py
pycamunda/request.py
pycamunda/resource.py
pycamunda/signal.py
pycamunda/task.py
pycamunda/telemetry.py
pycamunda/tenant.py
pycamunda/user.py
pycamunda/variable.py
pycamunda/version.py
pycamunda-0.6.1.dist-info/LICENSE
pycamunda-0.6.1.dist-info/METADATA
pycamunda-0.6.1.dist-info/WHEEL
pycamunda-0.6.1.dist-info/top_level.txt
pycamunda-0.6.1.dist-info/RECORD
