Metadata-Version: 2.1
Name: pycamunda
Version: 0.6.1
Summary: A high-level framework for communicating with the workflow and decision automation engine Camunda.
Home-page: https://github.com/pklauke/pycamunda
Author: Peter Klauke
License: UNKNOWN
Platform: UNKNOWN
Classifier: Programming Language :: Python :: 3
Classifier: License :: OSI Approved :: MIT License
Classifier: Operating System :: OS Independent
Requires-Python: >=3.7
Requires-Dist: requests (>=2.0.0)
